dtsdk/__init__.py
dtsdk/sdk.py
test/__init__.py
test/test_dtsdk.py
dtsdk-2.0.0.dist-info/LICENSE
dtsdk-2.0.0.dist-info/METADATA
dtsdk-2.0.0.dist-info/WHEEL
dtsdk-2.0.0.dist-info/top_level.txt
dtsdk-2.0.0.dist-info/RECORD
