Metadata-Version: 2.1
Name: dtsdk
Version: 2.0.0
Summary: DataTower.ai SDK for Python
Home-page: https://github.com/lovinjoy/datatower.ai-python
Author: DataTower.ai, Inc.
Author-email: contact@lovinjoy.com
License: Apache
Platform: all
Classifier: License :: OSI Approved :: Apache Software License
Classifier: Operating System :: OS Independent
Classifier: Intended Audience :: Developers
Classifier: Programming Language :: Python :: 2
Classifier: Programming Language :: Python :: 3
Classifier: Topic :: Software Development :: Libraries
License-File: LICENSE
Requires-Dist: requests
